examples/Agents/langchain_output.py
examples/LLM_API_call/anthropic_output.py
examples/LLM_API_call/mistral_output.py
examples/LLM_API_call/openai_output.py
tests/__init__.py
tests/test_main.py
tidyout/__init__.py
tidyout/main.py
tidyout/py.typed
tidyout-0.1.2.dist-info/licenses/LICENSE
tidyout-0.1.2.dist-info/METADATA
tidyout-0.1.2.dist-info/WHEEL
tidyout-0.1.2.dist-info/top_level.txt
tidyout-0.1.2.dist-info/RECORD
