Metadata-Version: 2.4
Name: tidyout
Version: 0.1.2
Summary: Clean and parse messy LLM output into structured JSON
Author-email: Mayank Soni <mayank.november@gmail.com>
License: MIT
Project-URL: Homepage, https://github.com/mayanksoni20/tidyout
Requires-Python: >=3.7
License-File: LICENSE
Requires-Dist: rich
Dynamic: license-file
